{
  "hash": "23b2a4ae",
  "configHash": "4885ec5a",
  "lockfileHash": "1b92da25",
  "browserHash": "2282117d",
  "optimized": {
    "react/jsx-dev-runtime": {
      "src": "../../node_modules/react/jsx-dev-runtime.js",
      "file": "react_jsx-dev-runtime.js",
      "fileHash": "004902e1",
      "needsInterop": true
    },
    "react": {
      "src": "../../node_modules/react/index.js",
      "file": "react.js",
      "fileHash": "18602f96",
      "needsInterop": true
    },
    "react-dom/client": {
      "src": "../../node_modules/react-dom/client.js",
      "file": "react-dom_client.js",
      "fileHash": "dbd335ff",
      "needsInterop": true
    },
    "react-router-dom": {
      "src": "../../node_modules/react-router-dom/dist/index.mjs",
      "file": "react-router-dom.js",
      "fileHash": "7e6f9828",
      "needsInterop": false
    },
    "axios": {
      "src": "../../node_modules/axios/index.js",
      "file": "axios.js",
      "fileHash": "80b9da6a",
      "needsInterop": false
    },
    "zustand": {
      "src": "../../node_modules/zustand/esm/index.mjs",
      "file": "zustand.js",
      "fileHash": "ff4220ec",
      "needsInterop": false
    },
    "clsx": {
      "src": "../../node_modules/clsx/dist/clsx.mjs",
      "file": "clsx.js",
      "fileHash": "61a74648",
      "needsInterop": false
    },
    "zod": {
      "src": "../../node_modules/zod/index.js",
      "file": "zod.js",
      "fileHash": "547ba42c",
      "needsInterop": false
    },
    "react-icons/fi": {
      "src": "../../node_modules/react-icons/fi/index.mjs",
      "file": "react-icons_fi.js",
      "fileHash": "aeec84c1",
      "needsInterop": false
    }
  },
  "chunks": {
    "chunk-JF7IVAG4": {
      "file": "chunk-JF7IVAG4.js"
    },
    "chunk-4BPZ7PBZ": {
      "file": "chunk-4BPZ7PBZ.js"
    },
    "chunk-G3PMV62Z": {
      "file": "chunk-G3PMV62Z.js"
    }
  }
}